README.rst
setup.cfg
setup.py
docs/conf.py
pasam/__init__.py
pasam/_messages.py
pasam/_paths.py
pasam/_settings.py
pasam/lattice.py
pasam/pathgen.py
pasam/sampling.py
pasam/utils.py
pasam.egg-info/PKG-INFO
pasam.egg-info/SOURCES.txt
pasam.egg-info/dependency_links.txt
pasam.egg-info/requires.txt
pasam.egg-info/top_level.txt
tests/__init__.py
tests/test_lattice_Condition.py
tests/test_lattice_Lattice.py
tests/test_utils.py
venv/Lib/site-packages/cycler.py
venv/Lib/site-packages/imagesize.py
venv/Lib/site-packages/pylab.py
venv/Lib/site-packages/pyparsing.py
venv/Lib/site-packages/six.py
venv/Lib/site-packages/zipp.py
venv/Lib/site-packages/alabaster/__init__.py
venv/Lib/site-packages/alabaster/_version.py
venv/Lib/site-packages/alabaster/support.py
venv/Lib/site-packages/babel/__init__.py
venv/Lib/site-packages/babel/_compat.py
venv/Lib/site-packages/babel/core.py
venv/Lib/site-packages/babel/dates.py
venv/Lib/site-packages/babel/languages.py
venv/Lib/site-packages/babel/lists.py
venv/Lib/site-packages/babel/localedata.py
venv/Lib/site-packages/babel/numbers.py
venv/Lib/site-packages/babel/plural.py
venv/Lib/site-packages/babel/support.py
venv/Lib/site-packages/babel/units.py
venv/Lib/site-packages/babel/util.py
venv/Lib/site-packages/babel/localtime/__init__.py
venv/Lib/site-packages/babel/localtime/_unix.py
venv/Lib/site-packages/babel/localtime/_win32.py
venv/Lib/site-packages/babel/messages/__init__.py
venv/Lib/site-packages/babel/messages/catalog.py
venv/Lib/site-packages/babel/messages/checkers.py
venv/Lib/site-packages/babel/messages/extract.py
venv/Lib/site-packages/babel/messages/frontend.py
venv/Lib/site-packages/babel/messages/jslexer.py
venv/Lib/site-packages/babel/messages/mofile.py
venv/Lib/site-packages/babel/messages/plurals.py
venv/Lib/site-packages/babel/messages/pofile.py
venv/Lib/site-packages/bleach/__init__.py
venv/Lib/site-packages/bleach/callbacks.py
venv/Lib/site-packages/bleach/html5lib_shim.py
venv/Lib/site-packages/bleach/linkifier.py
venv/Lib/site-packages/bleach/sanitizer.py
venv/Lib/site-packages/bleach/utils.py
venv/Lib/site-packages/bleach/_vendor/__init__.py
