Metadata-Version: 2.1
Name: pasam
Version: 0.1.5
Summary: Path sampling package
Home-page: https://github.com/jaegglic/pasam
Author: Stefanie Marti, Christoph Jaeggli
Author-email: stefanie.marti@insel.ch, christoph.jaeggli@insel.ch
License: MIT License
Keywords: sampling,radiotherapy,delivery path
Platform: UNKNOWN
Classifier: Development Status :: 4 - Beta
Classifier: Environment :: Console
Classifier: Intended Audience :: Developers
Classifier: Natural Language :: English
Classifier: License :: OSI Approved :: MIT License
Classifier: Programming Language :: Python
Classifier: Programming Language :: Python :: 3.6
Classifier: Programming Language :: Python :: 3.7
Classifier: Programming Language :: Python :: 3.8
Classifier: Programming Language :: Python :: Implementation :: CPython
Classifier: Programming Language :: Python :: Implementation :: PyPy
Classifier: Topic :: Software Development
Requires-Python: >=3.6
